{
    "AX":{
        "error":0.0065457792,
        "error_type":"SEM",
        "filter_outliers_dict":{
            "filter_outliers":true,
            "iterations":1,
            "std_devs":2
        },
        "fit":"average",
        "value":0.0230145364
    },
    "CDD":{
        "error":0.0000164152,
        "error_type":"SEM",
        "filter_outliers_dict":{
            "filter_outliers":true,
            "iterations":1,
            "std_devs":10
        },
        "fit":"average",
        "value":0.0001012762
    },
    "H1":{
        "error":0.0044002239,
        "error_type":"SEM",
        "filter_outliers_dict":{
            "filter_outliers":true,
            "iterations":1,
            "std_devs":2
        },
        "fit":"average",
        "value":0.0307363551
    },
    "H2":{
        "error":0.0135181572,
        "error_type":"SEM",
        "filter_outliers_dict":{
            "filter_outliers":true,
            "iterations":1,
            "std_devs":2
        },
        "fit":"average",
        "value":0.0109853083
    },
    "L1":{
        "error":0.0029933237,
        "error_type":"SEM",
        "filter_outliers_dict":{
            "filter_outliers":true,
            "iterations":1,
            "std_devs":2
        },
        "fit":"average",
        "value":-0.0375418129
    },
    "L2":{
        "error":0.0065982375,
        "error_type":"SEM",
        "filter_outliers_dict":{
            "filter_outliers":true,
            "iterations":1,
            "std_devs":2
        },
        "fit":"average",
        "value":-0.0354741583
    }
}