{
    "Ar36":{
        "error":0.0006501026,
        "error_type":"SEM",
        "filter_outliers_dict":{
            "filter_outliers":true,
            "iterations":1,
            "std_devs":2
        },
        "fit":"Linear",
        "value":0.0093835795
    },
    "Ar37":{
        "error":0.0252977963,
        "error_type":"SEM",
        "filter_outliers_dict":{
            "filter_outliers":true,
            "iterations":1,
            "std_devs":2
        },
        "fit":"linear",
        "value":0.0216046482
    },
    "Ar38":{
        "error":0.0129659535,
        "error_type":"SEM",
        "filter_outliers_dict":{
            "filter_outliers":true,
            "iterations":1,
            "std_devs":2
        },
        "fit":"linear",
        "value":0.1255678595
    },
    "Ar39":{
        "error":0.0396587094,
        "error_type":"SEM",
        "filter_outliers_dict":{
            "filter_outliers":true,
            "iterations":1,
            "std_devs":2
        },
        "fit":"Linear",
        "value":6.5218568184
    },
    "Ar40":{
        "error":0.0487106942,
        "error_type":"SEM",
        "filter_outliers_dict":{
            "filter_outliers":true,
            "iterations":1,
            "std_devs":2
        },
        "fit":"Linear",
        "value":190.9822995793
    },
    "Ar41":{
        "error":0.0181424737,
        "error_type":"SEM",
        "filter_outliers_dict":{
            "filter_outliers":true,
            "iterations":1,
            "std_devs":2
        },
        "fit":"Average",
        "value":0.0733727841
    }
}